my_utilities_dharanib282000/__init__.py
my_utilities_dharanib282000/file_operations.py
my_utilities_dharanib282000/math_operations.py
my_utilities_dharanib282000/string_operations.py
tests/__init__.py
tests/test_file_operations.py
tests/test_math_operations.py
tests/test_string_operations.py
my_utilities_dharanib282000-0.1.0.dist-info/METADATA
my_utilities_dharanib282000-0.1.0.dist-info/WHEEL
my_utilities_dharanib282000-0.1.0.dist-info/top_level.txt
my_utilities_dharanib282000-0.1.0.dist-info/RECORD
