Metadata-Version: 2.1
Name: my-utilities-dharanib282000
Version: 0.1.0
Summary: A collection of utility functions for various tasks.
Home-page: https://github.com/yourusername/my_utilities
Author: dharanib
Author-email: dharanibalasubramanian28@gmail.com
Classifier: Programming Language :: Python :: 3
Classifier: License :: OSI Approved :: MIT License
Classifier: Operating System :: OS Independent
Requires-Python: >=3.6
